MANIFEST.in
setup.py
./tbstock/__init__.c
./tbstock/dataAcquisition/__init__.c
./tbstock/dataAcquisition/models.c
./tbstock/dataAcquisition/saveDataToMysql.c
./tbstock/dataAcquisition/stockDataCrawler.c
./tbstock/dataBacktest/__init__.c
./tbstock/dataBacktest/strategyBacktest.c
./tbstock/dataManagement/__init__.c
./tbstock/dataManagement/dataPreprocess.c
./tbstock/dataRelease/__init__.c
./tbstock/dataRelease/dataRelease.c
./tbstock/tradeStrategy/__init__.c
./tbstock/tradeStrategy/stockStrategy.c
./tbstock/utils/__init__.c
./tbstock/utils/utils.c
tbstock/__init__.c
tbstock/__init__.cpython-39-x86_64-linux-gnu.so
tbstock.egg-info/PKG-INFO
tbstock.egg-info/SOURCES.txt
tbstock.egg-info/dependency_links.txt
tbstock.egg-info/requires.txt
tbstock.egg-info/top_level.txt
tbstock/dataAcquisition/__init__.c
tbstock/dataAcquisition/__init__.cpython-39-x86_64-linux-gnu.so
tbstock/dataAcquisition/models.c
tbstock/dataAcquisition/models.cpython-39-x86_64-linux-gnu.so
tbstock/dataAcquisition/saveDataToMysql.c
tbstock/dataAcquisition/saveDataToMysql.cpython-39-x86_64-linux-gnu.so
tbstock/dataAcquisition/stockDataCrawler.c
tbstock/dataAcquisition/stockDataCrawler.cpython-39-x86_64-linux-gnu.so
tbstock/dataBacktest/__init__.c
tbstock/dataBacktest/__init__.cpython-39-x86_64-linux-gnu.so
tbstock/dataBacktest/strategyBacktest.c
tbstock/dataBacktest/strategyBacktest.cpython-39-x86_64-linux-gnu.so
tbstock/dataManagement/__init__.c
tbstock/dataManagement/__init__.cpython-39-x86_64-linux-gnu.so
tbstock/dataManagement/dataPreprocess.c
tbstock/dataManagement/dataPreprocess.cpython-39-x86_64-linux-gnu.so
tbstock/dataRelease/__init__.c
tbstock/dataRelease/__init__.cpython-39-x86_64-linux-gnu.so
tbstock/dataRelease/dataRelease.c
tbstock/dataRelease/dataRelease.cpython-39-x86_64-linux-gnu.so
tbstock/tradeStrategy/__init__.c
tbstock/tradeStrategy/__init__.cpython-39-x86_64-linux-gnu.so
tbstock/tradeStrategy/stockStrategy.c
tbstock/tradeStrategy/stockStrategy.cpython-39-x86_64-linux-gnu.so
tbstock/utils/__init__.c
tbstock/utils/__init__.cpython-39-x86_64-linux-gnu.so
tbstock/utils/utils.c
tbstock/utils/utils.cpython-39-x86_64-linux-gnu.so